prometheus_swarm/__init__.py
prometheus_swarm/types.py
prometheus_swarm/clients/__init__.py
prometheus_swarm/clients/anthropic_client.py
prometheus_swarm/clients/base_client.py
prometheus_swarm/clients/conversation_manager.py
prometheus_swarm/clients/localai_client.py
prometheus_swarm/clients/ollama_client.py
prometheus_swarm/clients/openai_client.py
prometheus_swarm/clients/openrouter_client.py
prometheus_swarm/clients/xai_client.py
prometheus_swarm/database/__init__.py
prometheus_swarm/database/config.py
prometheus_swarm/database/database.py
prometheus_swarm/database/models.py
prometheus_swarm/tools/__init__.py
prometheus_swarm/tools/execute_command/__init__.py
prometheus_swarm/tools/execute_command/definitions.py
prometheus_swarm/tools/execute_command/implementations.py
prometheus_swarm/tools/file_operations/__init__.py
prometheus_swarm/tools/file_operations/definitions.py
prometheus_swarm/tools/file_operations/implementations.py
prometheus_swarm/tools/general_operations/__init__.py
prometheus_swarm/tools/general_operations/definitions.py
prometheus_swarm/tools/general_operations/implementations.py
prometheus_swarm/tools/git_operations/__init__.py
prometheus_swarm/tools/git_operations/definitions.py
prometheus_swarm/tools/git_operations/implementations.py
prometheus_swarm/tools/github_operations/__init__.py
prometheus_swarm/tools/github_operations/definitions.py
prometheus_swarm/tools/github_operations/implementations.py
prometheus_swarm/tools/github_operations/parser.py
prometheus_swarm/tools/github_operations/templates.py
prometheus_swarm/tools/github_operations/templates_legacy.py
prometheus_swarm/tools/kno_sdk_wrapper/__init__.py
prometheus_swarm/tools/kno_sdk_wrapper/definitions.py
prometheus_swarm/tools/kno_sdk_wrapper/implementations.py
prometheus_swarm/tools/repo_operations/Types.py
prometheus_swarm/tools/repo_operations/__init__.py
prometheus_swarm/tools/repo_operations/definitions.py
prometheus_swarm/tools/repo_operations/implementations.py
prometheus_swarm-0.3.8.dist-info/METADATA
prometheus_swarm-0.3.8.dist-info/WHEEL
prometheus_swarm-0.3.8.dist-info/top_level.txt
prometheus_swarm-0.3.8.dist-info/RECORD
